protogenie/__init__.py
protogenie/cli.py
protogenie/cli_utils.py
protogenie/configs.py
protogenie/defaults.py
protogenie/dispatch.py
protogenie/io_utils.py
protogenie/postprocessing.py
protogenie/reader.py
protogenie/sentence_matchers.py
protogenie/splitters.py
protogenie/toolbox.py
protogenie-0.0.7.dist-info/METADATA
protogenie-0.0.7.dist-info/WHEEL
protogenie-0.0.7.dist-info/entry_points.txt
protogenie-0.0.7.dist-info/top_level.txt
protogenie-0.0.7.dist-info/RECORD
