Metadata-Version: 2.1
Name: protogenie
Version: 0.0.7
Summary: Pre-processing of NLP training corpora
Home-page: https://github.com/ponteineptique/nlp-pie-taggers
Author: Thibault Clérice
License: MIT
Platform: UNKNOWN
Classifier: License :: OSI Approved :: MIT License
Classifier: Programming Language :: Python
Classifier: Programming Language :: Python :: 3
Classifier: Programming Language :: Python :: 3.6
Classifier: Programming Language :: Python :: 3.7
Classifier: Programming Language :: Python :: Implementation :: CPython
Classifier: Programming Language :: Python :: Implementation :: PyPy
Classifier: Topic :: Text Processing :: Linguistic
Requires-Python: >=3.6.0
Requires-Dist: click (<=8.0,>=7.0)
Requires-Dist: lxml
Requires-Dist: regex
Requires-Dist: dataclasses ; python_version < "3.7"
Requires-Dist: typing ; python_version < "3.7"
